kapital/__init__.py
kapital/kapital.py
kapital-1.0.5.dist-info/LICENSE
kapital-1.0.5.dist-info/METADATA
kapital-1.0.5.dist-info/WHEEL
kapital-1.0.5.dist-info/top_level.txt
kapital-1.0.5.dist-info/RECORD
