Metadata-Version: 2.1
Name: kapital
Version: 1.0.5
Summary: A simple client for the Kapital payment gateway.
Home-page: https://github.com/kazimovzaman2/kapital-python
Author: Zaman Kazimov
Author-email: kazimovzaman2@gmail.com
License-File: LICENSE
Requires-Dist: requests
